[
  {
    "f1_score_micro": 0.7341772151898733,
    "f1_score_macro": 0.6972455648926238,
    "f1_score_weighted": 0.7066166744475568,
    "f1_score_0": 0.33333333333333337,
    "f1_score_1": 0.888888888888889,
    "f1_score_2": 0.8571428571428571,
    "f1_score_3": 0.823529411764706,
    "f1_score_4": 0.5833333333333334,
    "precision_score_micro": 0.9354838709677419,
    "precision_score_macro": 0.9555555555555555,
    "precision_score_weighted": 0.9629629629629629,
    "precision_score_0": 1.0,
    "precision_score_1": 1.0,
    "precision_score_2": 1.0,
    "precision_score_3": 0.7777777777777778,
    "precision_score_4": 1.0,
    "recall_score_micro": 0.6041666666666666,
    "recall_score_macro": 0.6073529411764705,
    "recall_score_weighted": 0.6041666666666666,
    "recall_score_0": 0.2,
    "recall_score_1": 0.8,
    "recall_score_2": 0.75,
    "recall_score_3": 0.875,
    "recall_score_4": 0.4117647058823529,
    "param_id": 0
  },
  {
    "f1_score_micro": 0.2295081967213115,
    "f1_score_macro": 0.16075471698113208,
    "f1_score_weighted": 0.1214622641509434,
    "f1_score_0": 0.19999999999999998,
    "f1_score_1": 0.0,
    "f1_score_2": 0.3018867924528302,
    "f1_score_3": 0.3018867924528302,
    "f1_score_4": 0.0,
    "precision_score_micro": 0.15555555555555556,
    "precision_score_macro": 0.09333333333333334,
    "precision_score_weighted": 0.07083333333333335,
    "precision_score_0": 0.1111111111111111,
    "precision_score_1": 0.0,
    "precision_score_2": 0.17777777777777778,
    "precision_score_3": 0.17777777777777778,
    "precision_score_4": 0.0,
    "recall_score_micro": 0.4375,
    "recall_score_macro": 0.6,
    "recall_score_weighted": 0.4375,
    "recall_score_0": 1.0,
    "recall_score_1": 0.0,
    "recall_score_2": 1.0,
    "recall_score_3": 1.0,
    "recall_score_4": 0.0,
    "param_id": 1
  },
  {
    "f1_score_micro": 0.36231884057971014,
    "f1_score_macro": 0.17005477784540474,
    "f1_score_weighted": 0.2445348955163319,
    "f1_score_0": 0.0,
    "f1_score_1": 0.0,
    "f1_score_2": 0.0,
    "f1_score_3": 0.3018867924528302,
    "f1_score_4": 0.5483870967741935,
    "precision_score_micro": 0.2777777777777778,
    "precision_score_macro": 0.11111111111111112,
    "precision_score_weighted": 0.16342592592592595,
    "precision_score_0": 0.0,
    "precision_score_1": 0.0,
    "precision_score_2": 0.0,
    "precision_score_3": 0.17777777777777778,
    "precision_score_4": 0.37777777777777777,
    "recall_score_micro": 0.5208333333333334,
    "recall_score_macro": 0.4,
    "recall_score_weighted": 0.5208333333333334,
    "recall_score_0": 0.0,
    "recall_score_1": 0.0,
    "recall_score_2": 0.0,
    "recall_score_3": 1.0,
    "recall_score_4": 1.0,
    "param_id": 2
  },
  {
    "f1_score_micro": 0.18840579710144925,
    "f1_score_macro": 0.10037735849056603,
    "f1_score_weighted": 0.07114779874213836,
    "f1_score_0": 0.19999999999999998,
    "f1_score_1": 0.0,
    "f1_score_2": 0.3018867924528302,
    "f1_score_3": 0.0,
    "f1_score_4": 0.0,
    "precision_score_micro": 0.14444444444444443,
    "precision_score_macro": 0.057777777777777775,
    "precision_score_weighted": 0.04120370370370371,
    "precision_score_0": 0.1111111111111111,
    "precision_score_1": 0.0,
    "precision_score_2": 0.17777777777777778,
    "precision_score_3": 0.0,
    "precision_score_4": 0.0,
    "recall_score_micro": 0.2708333333333333,
    "recall_score_macro": 0.4,
    "recall_score_weighted": 0.2708333333333333,
    "recall_score_0": 1.0,
    "recall_score_1": 0.0,
    "recall_score_2": 1.0,
    "recall_score_3": 0.0,
    "recall_score_4": 0.0,
    "param_id": 3
  },
  {
    "f1_score_micro": 0.7341772151898733,
    "f1_score_macro": 0.6972455648926238,
    "f1_score_weighted": 0.7066166744475568,
    "f1_score_0": 0.33333333333333337,
    "f1_score_1": 0.888888888888889,
    "f1_score_2": 0.8571428571428571,
    "f1_score_3": 0.823529411764706,
    "f1_score_4": 0.5833333333333334,
    "precision_score_micro": 0.9354838709677419,
    "precision_score_macro": 0.9555555555555555,
    "precision_score_weighted": 0.9629629629629629,
    "precision_score_0": 1.0,
    "precision_score_1": 1.0,
    "precision_score_2": 1.0,
    "precision_score_3": 0.7777777777777778,
    "precision_score_4": 1.0,
    "recall_score_micro": 0.6041666666666666,
    "recall_score_macro": 0.6073529411764705,
    "recall_score_weighted": 0.6041666666666666,
    "recall_score_0": 0.2,
    "recall_score_1": 0.8,
    "recall_score_2": 0.75,
    "recall_score_3": 0.875,
    "recall_score_4": 0.4117647058823529,
    "param_id": 4
  },
  {
    "f1_score_micro": 0.6428571428571428,
    "f1_score_macro": 0.6120148856990962,
    "f1_score_weighted": 0.6244269908619462,
    "f1_score_0": 0.33333333333333337,
    "f1_score_1": 0.7368421052631579,
    "f1_score_2": 0.5454545454545454,
    "f1_score_3": 0.7777777777777778,
    "f1_score_4": 0.6666666666666666,
    "precision_score_micro": 0.8709677419354839,
    "precision_score_macro": 0.9333333333333333,
    "precision_score_weighted": 0.9245283018867925,
    "precision_score_0": 1.0,
    "precision_score_1": 1.0,
    "precision_score_2": 1.0,
    "precision_score_3": 1.0,
    "precision_score_4": 0.6666666666666666,
    "recall_score_micro": 0.5094339622641509,
    "recall_score_macro": 0.4922727272727273,
    "recall_score_weighted": 0.5094339622641509,
    "recall_score_0": 0.2,
    "recall_score_1": 0.5833333333333334,
    "recall_score_2": 0.375,
    "recall_score_3": 0.6363636363636364,
    "recall_score_4": 0.6666666666666666,
    "param_id": 0
  },
  {
    "f1_score_micro": 0.3404255319148936,
    "f1_score_macro": 0.228798411122145,
    "f1_score_weighted": 0.2362331603305166,
    "f1_score_0": 0.0,
    "f1_score_1": 0.4210526315789474,
    "f1_score_2": 0.3018867924528302,
    "f1_score_3": 0.0,
    "f1_score_4": 0.4210526315789474,
    "precision_score_micro": 0.23703703703703705,
    "precision_score_macro": 0.1422222222222222,
    "precision_score_weighted": 0.14758909853249477,
    "precision_score_0": 0.0,
    "precision_score_1": 0.26666666666666666,
    "precision_score_2": 0.17777777777777778,
    "precision_score_3": 0.0,
    "precision_score_4": 0.26666666666666666,
    "recall_score_micro": 0.6037735849056604,
    "recall_score_macro": 0.6,
    "recall_score_weighted": 0.6037735849056604,
    "recall_score_0": 0.0,
    "recall_score_1": 1.0,
    "recall_score_2": 1.0,
    "recall_score_3": 0.0,
    "recall_score_4": 1.0,
    "param_id": 1
  },
  {
    "f1_score_micro": 0.30769230769230765,
    "f1_score_macro": 0.1569377990430622,
    "f1_score_weighted": 0.16394330594926423,
    "f1_score_0": 0.3636363636363636,
    "f1_score_1": 0.0,
    "f1_score_2": 0.0,
    "f1_score_3": 0.0,
    "f1_score_4": 0.4210526315789474,
    "precision_score_micro": 0.24444444444444444,
    "precision_score_macro": 0.09777777777777777,
    "precision_score_weighted": 0.10230607966457024,
    "precision_score_0": 0.2222222222222222,
    "precision_score_1": 0.0,
    "precision_score_2": 0.0,
    "precision_score_3": 0.0,
    "precision_score_4": 0.26666666666666666,
    "recall_score_micro": 0.41509433962264153,
    "recall_score_macro": 0.4,
    "recall_score_weighted": 0.41509433962264153,
    "recall_score_0": 1.0,
    "recall_score_1": 0.0,
    "recall_score_2": 0.0,
    "recall_score_3": 0.0,
    "recall_score_4": 1.0,
    "param_id": 2
  },
  {
    "f1_score_micro": 0.3404255319148936,
    "f1_score_macro": 0.228798411122145,
    "f1_score_weighted": 0.2362331603305166,
    "f1_score_0": 0.0,
    "f1_score_1": 0.4210526315789474,
    "f1_score_2": 0.3018867924528302,
    "f1_score_3": 0.0,
    "f1_score_4": 0.4210526315789474,
    "precision_score_micro": 0.23703703703703705,
    "precision_score_macro": 0.1422222222222222,
    "precision_score_weighted": 0.14758909853249477,
    "precision_score_0": 0.0,
    "precision_score_1": 0.26666666666666666,
    "precision_score_2": 0.17777777777777778,
    "precision_score_3": 0.0,
    "precision_score_4": 0.26666666666666666,
    "recall_score_micro": 0.6037735849056604,
    "recall_score_macro": 0.6,
    "recall_score_weighted": 0.6037735849056604,
    "recall_score_0": 0.0,
    "recall_score_1": 1.0,
    "recall_score_2": 1.0,
    "recall_score_3": 0.0,
    "recall_score_4": 1.0,
    "param_id": 3
  },
  {
    "f1_score_micro": 0.6428571428571428,
    "f1_score_macro": 0.6120148856990962,
    "f1_score_weighted": 0.6244269908619462,
    "f1_score_0": 0.33333333333333337,
    "f1_score_1": 0.7368421052631579,
    "f1_score_2": 0.5454545454545454,
    "f1_score_3": 0.7777777777777778,
    "f1_score_4": 0.6666666666666666,
    "precision_score_micro": 0.8709677419354839,
    "precision_score_macro": 0.9333333333333333,
    "precision_score_weighted": 0.9245283018867925,
    "precision_score_0": 1.0,
    "precision_score_1": 1.0,
    "precision_score_2": 1.0,
    "precision_score_3": 1.0,
    "precision_score_4": 0.6666666666666666,
    "recall_score_micro": 0.5094339622641509,
    "recall_score_macro": 0.4922727272727273,
    "recall_score_weighted": 0.5094339622641509,
    "recall_score_0": 0.2,
    "recall_score_1": 0.5833333333333334,
    "recall_score_2": 0.375,
    "recall_score_3": 0.6363636363636364,
    "recall_score_4": 0.6666666666666666,
    "param_id": 4
  },
  {
    "f1_score_micro": 0.6829268292682927,
    "f1_score_macro": 0.6564213564213564,
    "f1_score_weighted": 0.6668647256882551,
    "f1_score_0": 0.2857142857142857,
    "f1_score_1": 0.6666666666666666,
    "f1_score_2": 0.9090909090909091,
    "f1_score_3": 0.7777777777777778,
    "f1_score_4": 0.6428571428571429,
    "precision_score_micro": 0.9032258064516129,
    "precision_score_macro": 0.95,
    "precision_score_weighted": 0.9215686274509803,
    "precision_score_0": 1.0,
    "precision_score_1": 1.0,
    "precision_score_2": 1.0,
    "precision_score_3": 1.0,
    "precision_score_4": 0.75,
    "recall_score_micro": 0.5490196078431373,
    "recall_score_macro": 0.5397727272727273,
    "recall_score_weighted": 0.5490196078431373,
    "recall_score_0": 0.16666666666666666,
    "recall_score_1": 0.5,
    "recall_score_2": 0.8333333333333334,
    "recall_score_3": 0.6363636363636364,
    "recall_score_4": 0.5625,
    "param_id": 0
  },
  {
    "f1_score_micro": 0.3971631205673759,
    "f1_score_macro": 0.18912855910267473,
    "f1_score_weighted": 0.2636485137627096,
    "f1_score_0": 0.0,
    "f1_score_1": 0.4210526315789474,
    "f1_score_2": 0.0,
    "f1_score_3": 0.0,
    "f1_score_4": 0.5245901639344263,
    "precision_score_micro": 0.3111111111111111,
    "precision_score_macro": 0.12444444444444444,
    "precision_score_weighted": 0.17429193899782136,
    "precision_score_0": 0.0,
    "precision_score_1": 0.26666666666666666,
    "precision_score_2": 0.0,
    "precision_score_3": 0.0,
    "precision_score_4": 0.35555555555555557,
    "recall_score_micro": 0.5490196078431373,
    "recall_score_macro": 0.4,
    "recall_score_weighted": 0.5490196078431373,
    "recall_score_0": 0.0,
    "recall_score_1": 1.0,
    "recall_score_2": 0.0,
    "recall_score_3": 0.0,
    "recall_score_4": 1.0,
    "param_id": 1
  },
  {
    "f1_score_micro": 0.125,
    "f1_score_macro": 0.047058823529411764,
    "f1_score_weighted": 0.027681660899653977,
    "f1_score_0": 0.23529411764705882,
    "f1_score_1": 0.0,
    "f1_score_2": 0.0,
    "f1_score_3": 0.0,
    "f1_score_4": 0.0,
    "precision_score_micro": 0.13333333333333333,
    "precision_score_macro": 0.026666666666666665,
    "precision_score_weighted": 0.01568627450980392,
    "precision_score_0": 0.13333333333333333,
    "precision_score_1": 0.0,
    "precision_score_2": 0.0,
    "precision_score_3": 0.0,
    "precision_score_4": 0.0,
    "recall_score_micro": 0.11764705882352941,
    "recall_score_macro": 0.2,
    "recall_score_weighted": 0.11764705882352941,
    "recall_score_0": 1.0,
    "recall_score_1": 0.0,
    "recall_score_2": 0.0,
    "recall_score_3": 0.0,
    "recall_score_4": 0.0,
    "param_id": 2
  },
  {
    "f1_score_micro": 0.3655913978494623,
    "f1_score_macro": 0.23618738263208652,
    "f1_score_weighted": 0.29133017466236355,
    "f1_score_0": 0.0,
    "f1_score_1": 0.4210526315789474,
    "f1_score_2": 0.23529411764705882,
    "f1_score_3": 0.0,
    "f1_score_4": 0.5245901639344263,
    "precision_score_micro": 0.2518518518518518,
    "precision_score_macro": 0.1511111111111111,
    "precision_score_weighted": 0.18997821350762528,
    "precision_score_0": 0.0,
    "precision_score_1": 0.26666666666666666,
    "precision_score_2": 0.13333333333333333,
    "precision_score_3": 0.0,
    "precision_score_4": 0.35555555555555557,
    "recall_score_micro": 0.6666666666666666,
    "recall_score_macro": 0.6,
    "recall_score_weighted": 0.6666666666666666,
    "recall_score_0": 0.0,
    "recall_score_1": 1.0,
    "recall_score_2": 1.0,
    "recall_score_3": 0.0,
    "recall_score_4": 1.0,
    "param_id": 3
  },
  {
    "f1_score_micro": 0.6829268292682927,
    "f1_score_macro": 0.6564213564213564,
    "f1_score_weighted": 0.6668647256882551,
    "f1_score_0": 0.2857142857142857,
    "f1_score_1": 0.6666666666666666,
    "f1_score_2": 0.9090909090909091,
    "f1_score_3": 0.7777777777777778,
    "f1_score_4": 0.6428571428571429,
    "precision_score_micro": 0.9032258064516129,
    "precision_score_macro": 0.95,
    "precision_score_weighted": 0.9215686274509803,
    "precision_score_0": 1.0,
    "precision_score_1": 1.0,
    "precision_score_2": 1.0,
    "precision_score_3": 1.0,
    "precision_score_4": 0.75,
    "recall_score_micro": 0.5490196078431373,
    "recall_score_macro": 0.5397727272727273,
    "recall_score_weighted": 0.5490196078431373,
    "recall_score_0": 0.16666666666666666,
    "recall_score_1": 0.5,
    "recall_score_2": 0.8333333333333334,
    "recall_score_3": 0.6363636363636364,
    "recall_score_4": 0.5625,
    "param_id": 4
  },
  {
    "f1_score_micro": 0.7228915662650603,
    "f1_score_macro": 0.6811194653299916,
    "f1_score_weighted": 0.7051938356529621,
    "f1_score_0": 0.2857142857142857,
    "f1_score_1": 0.8421052631578948,
    "f1_score_2": 0.8333333333333333,
    "f1_score_3": 0.7777777777777778,
    "f1_score_4": 0.6666666666666666,
    "precision_score_micro": 0.8333333333333334,
    "precision_score_macro": 0.8940170940170941,
    "precision_score_weighted": 0.8657937806873978,
    "precision_score_0": 1.0,
    "precision_score_1": 1.0,
    "precision_score_2": 1.0,
    "precision_score_3": 0.7777777777777778,
    "precision_score_4": 0.6923076923076923,
    "recall_score_micro": 0.6382978723404256,
    "recall_score_macro": 0.6057720057720057,
    "recall_score_weighted": 0.6382978723404256,
    "recall_score_0": 0.16666666666666666,
    "recall_score_1": 0.7272727272727273,
    "recall_score_2": 0.7142857142857143,
    "recall_score_3": 0.7777777777777778,
    "recall_score_4": 0.6428571428571429,
    "param_id": 0
  },
  {
    "f1_score_micro": 0.36496350364963503,
    "f1_score_macro": 0.1734866828087167,
    "f1_score_weighted": 0.2333084333625264,
    "f1_score_0": 0.0,
    "f1_score_1": 0.39285714285714285,
    "f1_score_2": 0.0,
    "f1_score_3": 0.0,
    "f1_score_4": 0.4745762711864407,
    "precision_score_micro": 0.2777777777777778,
    "precision_score_macro": 0.11111111111111112,
    "precision_score_weighted": 0.14988179669030732,
    "precision_score_0": 0.0,
    "precision_score_1": 0.24444444444444444,
    "precision_score_2": 0.0,
    "precision_score_3": 0.0,
    "precision_score_4": 0.3111111111111111,
    "recall_score_micro": 0.5319148936170213,
    "recall_score_macro": 0.4,
    "recall_score_weighted": 0.5319148936170213,
    "recall_score_0": 0.0,
    "recall_score_1": 1.0,
    "recall_score_2": 0.0,
    "recall_score_3": 0.0,
    "recall_score_4": 1.0,
    "param_id": 1
  },
  {
    "f1_score_micro": 0.291970802919708,
    "f1_score_macro": 0.1419740777666999,
    "f1_score_weighted": 0.1714006915423941,
    "f1_score_0": 0.23529411764705882,
    "f1_score_1": 0.0,
    "f1_score_2": 0.0,
    "f1_score_3": 0.0,
    "f1_score_4": 0.4745762711864407,
    "precision_score_micro": 0.2222222222222222,
    "precision_score_macro": 0.08888888888888888,
    "precision_score_weighted": 0.10969267139479906,
    "precision_score_0": 0.13333333333333333,
    "precision_score_1": 0.0,
    "precision_score_2": 0.0,
    "precision_score_3": 0.0,
    "precision_score_4": 0.3111111111111111,
    "recall_score_micro": 0.425531914893617,
    "recall_score_macro": 0.4,
    "recall_score_weighted": 0.425531914893617,
    "recall_score_0": 1.0,
    "recall_score_1": 0.0,
    "recall_score_2": 0.0,
    "recall_score_3": 0.0,
    "recall_score_4": 1.0,
    "param_id": 2
  },
  {
    "f1_score_micro": 0.36496350364963503,
    "f1_score_macro": 0.1734866828087167,
    "f1_score_weighted": 0.2333084333625264,
    "f1_score_0": 0.0,
    "f1_score_1": 0.39285714285714285,
    "f1_score_2": 0.0,
    "f1_score_3": 0.0,
    "f1_score_4": 0.4745762711864407,
    "precision_score_micro": 0.2777777777777778,
    "precision_score_macro": 0.11111111111111112,
    "precision_score_weighted": 0.14988179669030732,
    "precision_score_0": 0.0,
    "precision_score_1": 0.24444444444444444,
    "precision_score_2": 0.0,
    "precision_score_3": 0.0,
    "precision_score_4": 0.3111111111111111,
    "recall_score_micro": 0.5319148936170213,
    "recall_score_macro": 0.4,
    "recall_score_weighted": 0.5319148936170213,
    "recall_score_0": 0.0,
    "recall_score_1": 1.0,
    "recall_score_2": 0.0,
    "recall_score_3": 0.0,
    "recall_score_4": 1.0,
    "param_id": 3
  },
  {
    "f1_score_micro": 0.7228915662650603,
    "f1_score_macro": 0.6811194653299916,
    "f1_score_weighted": 0.7051938356529621,
    "f1_score_0": 0.2857142857142857,
    "f1_score_1": 0.8421052631578948,
    "f1_score_2": 0.8333333333333333,
    "f1_score_3": 0.7777777777777778,
    "f1_score_4": 0.6666666666666666,
    "precision_score_micro": 0.8333333333333334,
    "precision_score_macro": 0.8940170940170941,
    "precision_score_weighted": 0.8657937806873978,
    "precision_score_0": 1.0,
    "precision_score_1": 1.0,
    "precision_score_2": 1.0,
    "precision_score_3": 0.7777777777777778,
    "precision_score_4": 0.6923076923076923,
    "recall_score_micro": 0.6382978723404256,
    "recall_score_macro": 0.6057720057720057,
    "recall_score_weighted": 0.6382978723404256,
    "recall_score_0": 0.16666666666666666,
    "recall_score_1": 0.7272727272727273,
    "recall_score_2": 0.7142857142857143,
    "recall_score_3": 0.7777777777777778,
    "recall_score_4": 0.6428571428571429,
    "param_id": 4
  },
  {
    "f1_score_micro": 0.7674418604651163,
    "f1_score_macro": 0.6660342555994729,
    "f1_score_weighted": 0.7747796808666373,
    "f1_score_0": 0.3333333333333333,
    "f1_score_1": 0.9,
    "f1_score_2": 0.5,
    "f1_score_3": 0.8695652173913043,
    "f1_score_4": 0.7272727272727272,
    "precision_score_micro": 0.8048780487804879,
    "precision_score_macro": 0.7818181818181819,
    "precision_score_weighted": 0.847979797979798,
    "precision_score_0": 0.25,
    "precision_score_1": 1.0,
    "precision_score_2": 1.0,
    "precision_score_3": 0.9090909090909091,
    "precision_score_4": 0.75,
    "recall_score_micro": 0.7333333333333333,
    "recall_score_macro": 0.6381461675579323,
    "recall_score_weighted": 0.7333333333333333,
    "recall_score_0": 0.5,
    "recall_score_1": 0.8181818181818182,
    "recall_score_2": 0.3333333333333333,
    "recall_score_3": 0.8333333333333334,
    "recall_score_4": 0.7058823529411765,
    "param_id": 0
  },
  {
    "f1_score_micro": 0.45161290322580644,
    "f1_score_macro": 0.21814207650273226,
    "f1_score_weighted": 0.3409350333940498,
    "f1_score_0": 0.0,
    "f1_score_1": 0.5333333333333333,
    "f1_score_2": 0.0,
    "f1_score_3": 0.0,
    "f1_score_4": 0.5573770491803279,
    "precision_score_micro": 0.4375,
    "precision_score_macro": 0.2772727272727272,
    "precision_score_weighted": 0.3904040404040404,
    "precision_score_0": 0.0,
    "precision_score_1": 1.0,
    "precision_score_2": 0.0,
    "precision_score_3": 0.0,
    "precision_score_4": 0.38636363636363635,
    "recall_score_micro": 0.4666666666666667,
    "recall_score_macro": 0.27272727272727276,
    "recall_score_weighted": 0.4666666666666667,
    "recall_score_0": 0.0,
    "recall_score_1": 0.36363636363636365,
    "recall_score_2": 0.0,
    "recall_score_3": 0.0,
    "recall_score_4": 1.0,
    "param_id": 1
  },
  {
    "f1_score_micro": 0.1807909604519774,
    "f1_score_macro": 0.12292321924144312,
    "f1_score_weighted": 0.11015315037516703,
    "f1_score_0": 0.08695652173913045,
    "f1_score_1": 0.4,
    "f1_score_2": 0.1276595744680851,
    "f1_score_3": 0.0,
    "f1_score_4": 0.0,
    "precision_score_micro": 0.12121212121212122,
    "precision_score_macro": 0.07272727272727272,
    "precision_score_weighted": 0.06767676767676768,
    "precision_score_0": 0.045454545454545456,
    "precision_score_1": 0.25,
    "precision_score_2": 0.06818181818181818,
    "precision_score_3": 0.0,
    "precision_score_4": 0.0,
    "recall_score_micro": 0.35555555555555557,
    "recall_score_macro": 0.6,
    "recall_score_weighted": 0.35555555555555557,
    "recall_score_0": 1.0,
    "recall_score_1": 1.0,
    "recall_score_2": 1.0,
    "recall_score_3": 0.0,
    "recall_score_4": 0.0,
    "param_id": 2
  },
  {
    "f1_score_micro": 0.4554455445544554,
    "f1_score_macro": 0.2981420765027322,
    "f1_score_weighted": 0.3587128111718276,
    "f1_score_0": 0.4,
    "f1_score_1": 0.5333333333333333,
    "f1_score_2": 0.0,
    "f1_score_3": 0.0,
    "f1_score_4": 0.5573770491803279,
    "precision_score_micro": 0.4107142857142857,
    "precision_score_macro": 0.32727272727272727,
    "precision_score_weighted": 0.40151515151515155,
    "precision_score_0": 0.25,
    "precision_score_1": 1.0,
    "precision_score_2": 0.0,
    "precision_score_3": 0.0,
    "precision_score_4": 0.38636363636363635,
    "recall_score_micro": 0.5111111111111111,
    "recall_score_macro": 0.4727272727272728,
    "recall_score_weighted": 0.5111111111111111,
    "recall_score_0": 1.0,
    "recall_score_1": 0.36363636363636365,
    "recall_score_2": 0.0,
    "recall_score_3": 0.0,
    "recall_score_4": 1.0,
    "param_id": 3
  },
  {
    "f1_score_micro": 0.7674418604651163,
    "f1_score_macro": 0.6660342555994729,
    "f1_score_weighted": 0.7747796808666373,
    "f1_score_0": 0.3333333333333333,
    "f1_score_1": 0.9,
    "f1_score_2": 0.5,
    "f1_score_3": 0.8695652173913043,
    "f1_score_4": 0.7272727272727272,
    "precision_score_micro": 0.8048780487804879,
    "precision_score_macro": 0.7818181818181819,
    "precision_score_weighted": 0.847979797979798,
    "precision_score_0": 0.25,
    "precision_score_1": 1.0,
    "precision_score_2": 1.0,
    "precision_score_3": 0.9090909090909091,
    "precision_score_4": 0.75,
    "recall_score_micro": 0.7333333333333333,
    "recall_score_macro": 0.6381461675579323,
    "recall_score_weighted": 0.7333333333333333,
    "recall_score_0": 0.5,
    "recall_score_1": 0.8181818181818182,
    "recall_score_2": 0.3333333333333333,
    "recall_score_3": 0.8333333333333334,
    "recall_score_4": 0.7058823529411765,
    "param_id": 4
  }
]